chineseize_matplotlib/__init__.py
chineseize_matplotlib/chineseize_matplotlib.py
chineseize_matplotlib/fonts/IPA_Font_License_Agreement_v1.0.txt
chineseize_matplotlib/fonts/Readme_ipaexg00301.txt
chineseize_matplotlib/fonts/ipaexg.ttf
chineseize_matplotlib/fonts/simhei.ttf
chineseize_matplotlib-1.2.dist-info/LICENSE
chineseize_matplotlib-1.2.dist-info/METADATA
chineseize_matplotlib-1.2.dist-info/WHEEL
chineseize_matplotlib-1.2.dist-info/top_level.txt
chineseize_matplotlib-1.2.dist-info/RECORD
