Metadata-Version: 2.1
Name: chineseize-matplotlib
Version: 1.2
Summary: 自动设置matplotlib的中文字体
Home-page: https://github.com/cndeng/chineseize-matplotlib
Author: cndeng
Author-email: cndeng@foxmail.com
License: MIT License
Platform: UNKNOWN
